hussainn/__init__.py
hussainn/hussainn.py
hussainn-3.1.dist-info/METADATA
hussainn-3.1.dist-info/WHEEL
hussainn-3.1.dist-info/top_level.txt
hussainn-3.1.dist-info/RECORD
